model_metrics/__init__.py
model_metrics/logo.py
model_metrics/metrics_utils.py
model_metrics/model_calculator.py
model_metrics/model_evaluator.py
model_metrics/partial_dependence.py
model_metrics/plot_utils.py
model_metrics-0.0.5a3.dist-info/licenses/LICENSE.md
model_metrics-0.0.5a3.dist-info/METADATA
model_metrics-0.0.5a3.dist-info/WHEEL
model_metrics-0.0.5a3.dist-info/top_level.txt
model_metrics-0.0.5a3.dist-info/RECORD
