Metadata-Version: 2.4
Name: model_metrics
Version: 0.0.5a3
Summary: A Python library for model evaluation, performance tracking, and metric visualizations, supporting classification and regression models with robust analytics and reporting.
Author: Leonid Shpaner
Author-email: Leonid Shpaner <lshpaner@ucla.edu>
Project-URL: Source Code, https://github.com/lshpaner/model_metrics
Project-URL: Leonid Shpaner's Website, https://www.leonshpaner.com
Classifier: Programming Language :: Python :: 3
Classifier: License :: OSI Approved :: MIT License
Classifier: Operating System :: OS Independent
Requires-Python: >=3.7.4
License-File: LICENSE.md
Requires-Dist: matplotlib<3.11,>=3.5.3
Requires-Dist: numpy<2.2,>=1.21.6
Requires-Dist: pandas<2.3,>=1.3.5
Requires-Dist: plotly<5.25,>=5.18.0
Requires-Dist: scikit-learn<1.6,>=1.0.2
Requires-Dist: scipy<=1.14.0,>=1.8
Requires-Dist: statsmodels<0.15,>=0.13
Requires-Dist: shap<0.47,>=0.41.0
Requires-Dist: tqdm<4.68,>=4.66.4
Dynamic: author
Dynamic: license-file
Dynamic: requires-python
